rad/__init__.py
rad/optim.py
pytorch_rad-0.1.5.dist-info/LICENSE
pytorch_rad-0.1.5.dist-info/METADATA
pytorch_rad-0.1.5.dist-info/WHEEL
pytorch_rad-0.1.5.dist-info/top_level.txt
pytorch_rad-0.1.5.dist-info/RECORD
