Metadata-Version: 2.1
Name: pytorch-rad
Version: 0.1.5
Summary: A pytorch implementation of the optimizer RAD
Home-page: https://github.com/TobiasLv/RAD
Author: iDLab
Author-email: lyo.tobias@foxmail.com
Classifier: Programming Language :: Python :: 3
Classifier: License :: OSI Approved :: MIT License
Classifier: Operating System :: OS Independent
Requires-Python: >=3.6
License-File: LICENSE
Requires-Dist: torch
Requires-Dist: numpy
